OpentutorialGitPythonDjangoJiaocheng/README.md
OpentutorialGitPythonDjangoJiaocheng/__init__.py
OpentutorialGitPythonDjangoJiaocheng/__main__.py
OpentutorialGitPythonDjangoJiaocheng/file.epub
OpentutorialGitPythonDjangoJiaocheng/index.html
OpentutorialGitPythonDjangoJiaocheng/css/__init__.py
OpentutorialGitPythonDjangoJiaocheng/css/annotations.css
OpentutorialGitPythonDjangoJiaocheng/css/main.css
OpentutorialGitPythonDjangoJiaocheng/css/normalize.css
OpentutorialGitPythonDjangoJiaocheng/css/popup.css
OpentutorialGitPythonDjangoJiaocheng/font/__init__.py
OpentutorialGitPythonDjangoJiaocheng/font/fontello.eot
OpentutorialGitPythonDjangoJiaocheng/font/fontello.svg
OpentutorialGitPythonDjangoJiaocheng/font/fontello.ttf
OpentutorialGitPythonDjangoJiaocheng/font/fontello.woff
OpentutorialGitPythonDjangoJiaocheng/img/__init__.py
OpentutorialGitPythonDjangoJiaocheng/img/annotator-glyph-sprite.png
OpentutorialGitPythonDjangoJiaocheng/img/annotator-icon-sprite.png
OpentutorialGitPythonDjangoJiaocheng/img/apple-touch-icon.png
OpentutorialGitPythonDjangoJiaocheng/img/cancelfullscreen.png
OpentutorialGitPythonDjangoJiaocheng/img/close.png
OpentutorialGitPythonDjangoJiaocheng/img/fullscreen.png
OpentutorialGitPythonDjangoJiaocheng/img/loader.gif
OpentutorialGitPythonDjangoJiaocheng/img/menu-icon.png
OpentutorialGitPythonDjangoJiaocheng/img/save.png
OpentutorialGitPythonDjangoJiaocheng/img/saved.png
OpentutorialGitPythonDjangoJiaocheng/img/settings-s.png
OpentutorialGitPythonDjangoJiaocheng/img/settings.png
OpentutorialGitPythonDjangoJiaocheng/img/star.png
OpentutorialGitPythonDjangoJiaocheng/js/__init__.py
OpentutorialGitPythonDjangoJiaocheng/js/epub.js
OpentutorialGitPythonDjangoJiaocheng/js/epub.min.js
OpentutorialGitPythonDjangoJiaocheng/js/epub.min.map
OpentutorialGitPythonDjangoJiaocheng/js/hooks.min.js
OpentutorialGitPythonDjangoJiaocheng/js/hooks.min.map
OpentutorialGitPythonDjangoJiaocheng/js/reader.js
OpentutorialGitPythonDjangoJiaocheng/js/reader.js.map
opentutorial_git_python_django_jiaocheng-2024.3.3.0.dist-info/METADATA
opentutorial_git_python_django_jiaocheng-2024.3.3.0.dist-info/WHEEL
opentutorial_git_python_django_jiaocheng-2024.3.3.0.dist-info/entry_points.txt
opentutorial_git_python_django_jiaocheng-2024.3.3.0.dist-info/top_level.txt
opentutorial_git_python_django_jiaocheng-2024.3.3.0.dist-info/RECORD
